Metadata-Version: 2.1
Name: pyziper
Version: 0.3
Summary: pyziper a simple cli tools to help you to handle archive file ,like zipping and unzipping 
Home-page: https://github.com/AlphaBeta1906/pyziper
Author: fariz
Author-email: farizi1906@gmail.com
License: UNKNOWN
Download-URL: https://github.com/AlphaBeta1906/pyziper/archive/refs/tags/v0.3.tar.gz
Keywords: tools,cli,zip,7z,tar,archive
Platform: UNKNOWN
Classifier: Development Status :: 3 - Alpha
Classifier: Intended Audience :: Developers
Classifier: License :: OSI Approved :: MIT License
Classifier: Environment :: Console
Classifier: Programming Language :: Python :: 3.7
Classifier: Programming Language :: Python :: 3.8
Classifier: Programming Language :: Python :: 3.9
Classifier: Programming Language :: Python :: 3 :: Only
